odoo/addons/web_widget_progressbar_gradient/README.rst
odoo/addons/web_widget_progressbar_gradient/__init__.py
odoo/addons/web_widget_progressbar_gradient/__manifest__.py
odoo/addons/web_widget_progressbar_gradient/i18n/it.po
odoo/addons/web_widget_progressbar_gradient/i18n/web_widget_progressbar_gradient.pot
odoo/addons/web_widget_progressbar_gradient/readme/CONTRIBUTORS.md
odoo/addons/web_widget_progressbar_gradient/readme/DESCRIPTION.md
odoo/addons/web_widget_progressbar_gradient/readme/ROADMAP.md
odoo/addons/web_widget_progressbar_gradient/readme/USAGE.md
odoo/addons/web_widget_progressbar_gradient/static/description/icon.png
odoo/addons/web_widget_progressbar_gradient/static/description/index.html
odoo/addons/web_widget_progressbar_gradient/static/description/progressbar_gradient.png
odoo/addons/web_widget_progressbar_gradient/static/description/progressbar_gradient_inverse.png
odoo/addons/web_widget_progressbar_gradient/static/src/js/progressbar.esm.js
odoo/addons/web_widget_progressbar_gradient/static/src/scss/progressbar.scss
odoo/addons/web_widget_progressbar_gradient/static/src/xml/progressbar.xml
odoo_addon_web_widget_progressbar_gradient-16.0.1.0.0.5.dist-info/METADATA
odoo_addon_web_widget_progressbar_gradient-16.0.1.0.0.5.dist-info/WHEEL
odoo_addon_web_widget_progressbar_gradient-16.0.1.0.0.5.dist-info/top_level.txt
odoo_addon_web_widget_progressbar_gradient-16.0.1.0.0.5.dist-info/RECORD
